encryptor64/__init__.py
encryptor64/encryption.py
encryptor64-1.2.0.dist-info/DESCRIPTION.rst
encryptor64-1.2.0.dist-info/METADATA
encryptor64-1.2.0.dist-info/RECORD
encryptor64-1.2.0.dist-info/WHEEL
encryptor64-1.2.0.dist-info/metadata.json
encryptor64-1.2.0.dist-info/top_level.txt
